mman/CHECKSUM-SHA3-256.py
mman/__init__.py
mman/__main__.py
mman/man_common.py
mman/manenfb.py
mman/manenob.py
mman/manjpfb.py
mman/mman.py
mman-0.0.4.dist-info/LICENSE
mman-0.0.4.dist-info/METADATA
mman-0.0.4.dist-info/WHEEL
mman-0.0.4.dist-info/entry_points.txt
mman-0.0.4.dist-info/top_level.txt
mman-0.0.4.dist-info/RECORD
